rbamlib/__init__.py
rbamlib/constants.py
rbamlib/conv/Jcmu2K.py
rbamlib/conv/Kmu2Jc.py
rbamlib/conv/LK2al.py
rbamlib/conv/Lal2K.py
rbamlib/conv/__init__.py
rbamlib/conv/en2pc.py
rbamlib/conv/enral2mu.py
rbamlib/conv/mural2en.py
rbamlib/conv/mural2pc.py
rbamlib/conv/pc2en.py
rbamlib/conv/pcral2mu.py
rbamlib/models/__init__.py
rbamlib/models/dip/B.py
rbamlib/models/dip/B0.py
rbamlib/models/dip/T.py
rbamlib/models/dip/Y.py
rbamlib/models/dip/__init__.py
rbamlib/models/dll/A2016.py
rbamlib/models/dll/BA2000.py
rbamlib/models/dll/L2016.py
rbamlib/models/dll/O2014.py
rbamlib/models/dll/__init__.py
rbamlib/models/dxx/__init__.py
rbamlib/models/dxx/chorus/S2011.py
rbamlib/models/dxx/chorus/Z2019.py
rbamlib/models/dxx/chorus/__init__.py
rbamlib/models/dxx/emic/D2017.py
rbamlib/models/dxx/emic/__init__.py
rbamlib/models/dxx/hiss/S2011.py
rbamlib/models/dxx/hiss/S2015.py
rbamlib/models/dxx/hiss/Z2019.py
rbamlib/models/dxx/hiss/__init__.py
rbamlib/models/dxx/lightning/S2011.py
rbamlib/models/dxx/lightning/__init__.py
rbamlib/models/dxx/vlf/S2011.py
rbamlib/models/dxx/vlf/__init__.py
rbamlib/models/elec/VS1975.py
rbamlib/models/elec/__init__.py
rbamlib/models/ib/W2024.py
rbamlib/models/ib/__init__.py
rbamlib/models/lpp/CA1992.py
rbamlib/models/lpp/M2002.py
rbamlib/models/lpp/OBM2003.py
rbamlib/models/lpp/__init__.py
rbamlib/models/mag/TS2005_S.py
rbamlib/models/mag/TS2005_W.py
rbamlib/models/mag/__init__.py
rbamlib/models/mp/S1998.py
rbamlib/models/mp/__init__.py
rbamlib/models/ne/D2012.py
rbamlib/models/ne/__init__.py
rbamlib/models/pad/S2022.py
rbamlib/models/pad/__init__.py
rbamlib/models/tau/__init__.py
rbamlib/models/tau/chorus/G2012.py
rbamlib/models/tau/chorus/W2024.py
rbamlib/models/tau/chorus/__init__.py
rbamlib/models/tau/hiss/O2016.py
rbamlib/models/tau/hiss/__init__.py
rbamlib/motion/__init__.py
rbamlib/sim/__init__.py
rbamlib/utils/__init__.py
rbamlib/utils/fixfill.py
rbamlib/utils/idx.py
rbamlib/utils/parse_datetime.py
rbamlib/utils/storm_idx.py
rbamlib-25.4.dist-info/licenses/LICENSE
rbamlib-25.4.dist-info/METADATA
rbamlib-25.4.dist-info/WHEEL
rbamlib-25.4.dist-info/top_level.txt
rbamlib-25.4.dist-info/RECORD
