Metadata-Version: 2.4
Name: rbamlib
Version: 25.4
Summary: A lightweight, open-source Python library for the analysis and modeling of radiation belts.
Home-page: https://github.com/radiation-belts/rbamlib
Author: Alexander Drozdov
Author-email: adrozdov@ucla.edu
Classifier: Programming Language :: Python :: 3
Classifier: License :: OSI Approved :: BSD License
Classifier: Operating System :: OS Independent
Requires-Python: >=3.9
License-File: LICENSE
Requires-Dist: numpy
Requires-Dist: scipy
Dynamic: author
Dynamic: author-email
Dynamic: classifier
Dynamic: description
Dynamic: description-content-type
Dynamic: home-page
Dynamic: license-file
Dynamic: requires-dist
Dynamic: requires-python
Dynamic: summary
